anchorestig/__init__.py
anchorestig/general.py
anchorestig/generate.py
anchorestig/inputs.py
anchorestig/main.py
anchorestig/provision.py
anchorestig/review.py
anchorestig/runtime.py
anchorestig/static.py
anchorestig/vm.py
anchorestig/train-k8s-container/CHANGELOG.md
anchorestig/train-k8s-container/Gemfile
anchorestig/train-k8s-container/LICENSE
anchorestig/train-k8s-container/README.md
anchorestig/train-k8s-container/Rakefile
anchorestig/train-k8s-container/VERSION
anchorestig/train-k8s-container/sonar-project.properties
anchorestig/train-k8s-container/train-k8s-container.gemspec
anchorestig/train-k8s-container/.expeditor/config.yml
anchorestig/train-k8s-container/.expeditor/coverage.pipeline.yml
anchorestig/train-k8s-container/.expeditor/update_version.sh
anchorestig/train-k8s-container/.expeditor/verify.pipeline.yml
anchorestig/train-k8s-container/.expeditor/buildkite/coverage.sh
anchorestig/train-k8s-container/.expeditor/buildkite/run_linux_tests.sh
anchorestig/train-k8s-container/docs/README.md
anchorestig/train-k8s-container/lib/train-k8s-container.rb
anchorestig/train-k8s-container/lib/train/k8s/container/connection.rb
anchorestig/train-k8s-container/lib/train/k8s/container/kubectl_exec_client.rb
anchorestig/train-k8s-container/lib/train/k8s/container/platform.rb
anchorestig/train-k8s-container/lib/train/k8s/container/transport.rb
anchorestig/train-k8s-container/lib/train/k8s/container/version.rb
anchorestig/train-k8s-container/spec/spec_helper.rb
anchorestig/train-k8s-container/spec/train/k8s/container_spec.rb
anchorestig/train-k8s-container/spec/train/k8s/kubectl_exec_client_spec.rb
anchorestig/train-k8s-container/spec/train/k8s/container/connection_spec.rb
anchorestig/train-k8s-container/spec/train/k8s/container/platform_spec.rb
anchorestig/train-k8s-container/spec/train/k8s/container/transport_spec.rb
anchorestig-0.75.5.dist-info/licenses/LICENSE
anchorestig-0.75.5.dist-info/METADATA
anchorestig-0.75.5.dist-info/WHEEL
anchorestig-0.75.5.dist-info/entry_points.txt
anchorestig-0.75.5.dist-info/top_level.txt
anchorestig-0.75.5.dist-info/RECORD
